aiocloudlibrary/__init__.py
aiocloudlibrary/client.py
aiocloudlibrary/const.py
aiocloudlibrary-0.2.0.dist-info/LICENSE
aiocloudlibrary-0.2.0.dist-info/METADATA
aiocloudlibrary-0.2.0.dist-info/WHEEL
aiocloudlibrary-0.2.0.dist-info/top_level.txt
aiocloudlibrary-0.2.0.dist-info/RECORD
